{
  "results": {
    "tool": {
      "name": "playwright"
    },
    "summary": {
      "tests": 1,
      "passed": 0,
      "failed": 1,
      "pending": 0,
      "skipped": 0,
      "other": 0,
      "start": 1761908981674,
      "stop": 1761908993016,
      "suites": 0
    },
    "tests": [
      {
        "name": "loggedin - sheet - snapshot",
        "status": "failed",
        "duration": 10884,
        "start": 1761908982,
        "stop": 1761908992,
        "message": "Error: \u001b[2mexpect(\u001b[22m\u001b[31mreceived\u001b[39m\u001b[2m).\u001b[22mtoEqual\u001b[2m(\u001b[22m\u001b[32mexpected\u001b[39m\u001b[2m) // deep equality\u001b[22m\n\nExpected: \u001b[32m\"\"\u001b[39m\nReceived: \u001b[31m\"test text\"\u001b[39m",
        "trace": "Error: \u001b[2mexpect(\u001b[22m\u001b[31mreceived\u001b[39m\u001b[2m).\u001b[22mtoEqual\u001b[2m(\u001b[22m\u001b[32mexpected\u001b[39m\u001b[2m) // deep equality\u001b[22m\n\nExpected: \u001b[32m\"\"\u001b[39m\nReceived: \u001b[31m\"test text\"\u001b[39m\n    at /home/zuzanna/e2e-test-suite/e2e-tests/sheet_loggedin.spec.js:168:34",
        "rawStatus": "failed",
        "tags": [],
        "type": "e2e",
        "filePath": "/home/zuzanna/e2e-test-suite/e2e-tests/sheet_loggedin.spec.js",
        "retries": 0,
        "flaky": false,
        "steps": [],
        "suite": "chrome > sheet_loggedin.spec.js",
        "attachments": [],
        "stdout": [
          "ExpectError: \u001b[2mexpect(\u001b[22m\u001b[31mreceived\u001b[39m\u001b[2m).\u001b[22mtoEqual\u001b[2m(\u001b[22m\u001b[32mexpected\u001b[39m\u001b[2m) // deep equality\u001b[22m\n\nExpected: \u001b[32m\"\"\u001b[39m\nReceived: \u001b[31m\"test text\"\u001b[39m\n    at \u001b[90m/home/zuzanna/e2e-test-suite/\u001b[39me2e-tests/sheet_loggedin.spec.js:168:34 {\n  matcherResult: {\n    actual: \u001b[32m'test text'\u001b[39m,\n    expected: \u001b[32m''\u001b[39m,\n    message: \u001b[32m'\\x1B[2mexpect(\\x1B[22m\\x1B[31mreceived\\x1B[39m\\x1B[2m).\\x1B[22mtoEqual\\x1B[2m(\\x1B[22m\\x1B[32mexpected\\x1B[39m\\x1B[2m) // deep equality\\x1B[22m\\n'\u001b[39m +\n      \u001b[32m'\\n'\u001b[39m +\n      \u001b[32m'Expected: \\x1B[32m\"\"\\x1B[39m\\n'\u001b[39m +\n      \u001b[32m'Received: \\x1B[31m\"test text\"\\x1B[39m'\u001b[39m,\n    name: \u001b[32m'toEqual'\u001b[39m,\n    pass: \u001b[33mfalse\u001b[39m\n  },\n  \u001b[32mSymbol(step)\u001b[39m: {\n    stepId: \u001b[32m'expect@54'\u001b[39m,\n    category: \u001b[32m'expect'\u001b[39m,\n    title: \u001b[32m'expect.toEqual'\u001b[39m,\n    params: \u001b[90mundefined\u001b[39m,\n    infectParentStepsWithError: \u001b[90mundefined\u001b[39m,\n    boxedStack: \u001b[90mundefined\u001b[39m,\n    location: {\n      file: \u001b[32m'/home/zuzanna/e2e-test-suite/e2e-tests/sheet_loggedin.spec.js'\u001b[39m,\n      line: \u001b[33m168\u001b[39m,\n      column: \u001b[33m34\u001b[39m,\n      function: \u001b[90mundefined\u001b[39m\n    },\n    steps: [],\n    attachmentIndices: [],\n    complete: \u001b[36m[Function: complete]\u001b[39m,\n    endWallTime: \u001b[33m1761908992899\u001b[39m,\n    error: {\n      message: \u001b[32m'Error: \\x1B[2mexpect(\\x1B[22m\\x1B[31mreceived\\x1B[39m\\x1B[2m).\\x1B[22mtoEqual\\x1B[2m(\\x1B[22m\\x1B[32mexpected\\x1B[39m\\x1B[2m) // deep equality\\x1B[22m\\n'\u001b[39m +\n        \u001b[32m'\\n'\u001b[39m +\n        \u001b[32m'Expected: \\x1B[32m\"\"\\x1B[39m\\n'\u001b[39m +\n        \u001b[32m'Received: \\x1B[31m\"test text\"\\x1B[39m'\u001b[39m,\n      stack: \u001b[32m'Error: \\x1B[2mexpect(\\x1B[22m\\x1B[31mreceived\\x1B[39m\\x1B[2m).\\x1B[22mtoEqual\\x1B[2m(\\x1B[22m\\x1B[32mexpected\\x1B[39m\\x1B[2m) // deep equality\\x1B[22m\\n'\u001b[39m +\n        \u001b[32m'\\n'\u001b[39m +\n        \u001b[32m'Expected: \\x1B[32m\"\"\\x1B[39m\\n'\u001b[39m +\n        \u001b[32m'Received: \\x1B[31m\"test text\"\\x1B[39m\\n'\u001b[39m +\n        \u001b[32m'    at /home/zuzanna/e2e-test-suite/e2e-tests/sheet_loggedin.spec.js:168:34'\u001b[39m,\n      cause: \u001b[90mundefined\u001b[39m,\n      matcherResult: \u001b[36m[Object]\u001b[39m\n    }\n  }\n}\n"
        ],
        "stderr": [],
        "extra": {
          "annotations": []
        }
      }
    ]
  }
}
